superlogica/__init__.py
superlogica/resource_mapping.py
superlogica/superlogica.py
superlogica_api_wrapper-0.2.3.dist-info/LICENSE
superlogica_api_wrapper-0.2.3.dist-info/METADATA
superlogica_api_wrapper-0.2.3.dist-info/WHEEL
superlogica_api_wrapper-0.2.3.dist-info/top_level.txt
superlogica_api_wrapper-0.2.3.dist-info/RECORD
